ecologi/__init__.py
ecologi/ecologi.py
ecologi/py.typed
ecologi/types.py
ecologi_sdk-0.1.2.dist-info/METADATA
ecologi_sdk-0.1.2.dist-info/WHEEL
ecologi_sdk-0.1.2.dist-info/licenses/LICENSE.md
ecologi_sdk-0.1.2.dist-info/RECORD
