Metadata-Version: 2.1
Name: ecologi-sdk
Version: 0.1.2
Summary: Ecologi Python SDK
Project-URL: Source Code, https://github.com/owenvoke/ecologi-python-sdk
Project-URL: Issues, https://github.com/owenvoke/ecologi-python-sdk/issues
Author-email: Owen Voke <development@voke.dev>
License-File: LICENSE.md
Keywords: ecologi,sdk
Classifier: Intended Audience :: Developers
Classifier: License :: OSI Approved :: MIT License
Classifier: Programming Language :: Python :: 3 :: Only
Requires-Python: >=3.9.0
Requires-Dist: requests>=2.28.1
